mseep_prims-0.1.1.dist-info/licenses/LICENSE
server/__init__.py
server/config.py
server/main.py
server/prompts/__init__.py
server/prompts/python_programmer.py
server/sandbox/__init__.py
server/sandbox/downloader.py
server/sandbox/env.py
server/sandbox/runner.py
server/tools/__init__.py
server/tools/mount_file.py
server/tools/persist_artifact.py
server/tools/run_code.py
server/tools/workspace_inspect.py
mseep_prims-0.1.1.dist-info/METADATA
mseep_prims-0.1.1.dist-info/WHEEL
mseep_prims-0.1.1.dist-info/top_level.txt
mseep_prims-0.1.1.dist-info/RECORD
