Metadata-Version: 2.4
Name: mseep-prims
Version: 0.1.1
Summary: Python Runtime Interpreter MCP Server
Author-email: mseep <support@skydeck.ai>
License: MIT License
Requires-Python: >=3.13
License-File: LICENSE
Requires-Dist: fastmcp
Requires-Dist: aiohttp
Requires-Dist: aiofiles
Provides-Extra: dev
Requires-Dist: pytest>=7.4.0; extra == "dev"
Requires-Dist: pytest-asyncio>=0.21.0; extra == "dev"
Requires-Dist: pytest-cov>=4.1.0; extra == "dev"
Requires-Dist: pytest-mock>=3.11.0; extra == "dev"
Requires-Dist: pytest-timeout>=2.1.0; extra == "dev"
Requires-Dist: black>=23.7.0; extra == "dev"
Requires-Dist: isort>=5.12.0; extra == "dev"
Requires-Dist: ruff>=0.0.280; extra == "dev"
Requires-Dist: mypy>=1.5.0; extra == "dev"
Requires-Dist: bandit[toml]>=1.7.5; extra == "dev"
Requires-Dist: safety>=2.3.0; extra == "dev"
Requires-Dist: httpx>=0.24.0; extra == "dev"
Requires-Dist: pytest-httpx>=0.21.0; extra == "dev"
Requires-Dist: factory-boy>=3.3.0; extra == "dev"
Requires-Dist: freezegun>=1.2.0; extra == "dev"
Dynamic: license-file
